LICENSE.txt
MANIFEST.in
README.rst
dev_requirements.txt
requirements.txt
setup.py
backup_monkey/__init__.py
backup_monkey/cli.py
backup_monkey/core.py
backup_monkey/exceptions.py
backup_monkey.egg-info/PKG-INFO
backup_monkey.egg-info/SOURCES.txt
backup_monkey.egg-info/dependency_links.txt
backup_monkey.egg-info/entry_points.txt
backup_monkey.egg-info/not-zip-safe
backup_monkey.egg-info/requires.txt
backup_monkey.egg-info/top_level.txt