Metadata-Version: 1.1
Name: backup-monkey
Version: 1.0.0
Summary: A service that makes sure you have snapshots of all your EBS volumes
Home-page: https://github.com/Answers4AWS/backup-monkey
Author: Peter Sankauskas
Author-email: info@answersforaws.com
License: Apache License
